Modulos/Serial_Paralelo/serialParalelo.v
`timescale 1ns/1ps

module serialParalelo(
  clk, reset, enb,
  clk10,
  entrada,
  salidas
);

parameter cantBits = 8;

input wire clk;
input wire reset;
input wire enb;
input wire clk10;
input wire entrada;
output reg [7:0] salidas;

reg [3:0] contador;
reg [7:0] bits;

always @(posedge clk) begin
  if (reset) begin
    contador <= 0;
  end else if (enb) begin
    contador <= contador == 0 ? cantBits-1 : contador-1;
    bits[contador] <= entrada;
    if (contador ==  0) begin
      salidas <= {bits[cantBits-1:1], entrada};
    end
  end
end




endmodule

Modulos/Rx/GeneradorClk.v
`timescale 1ns/1ps

module GeneradorClk(
  clk, rst, enb,
  clk10, clk20, clk40
);


  input wire clk;
  input wire rst;
  input wire enb;

  output reg clk10;
  output reg clk20;
  output reg clk40;

  reg [2:0] cnt10;

  always @ (posedge clk) begin
    if (rst) begin
      cnt10 <= 3'd1;
      clk10 <= 1'b0;
      clk20 <= 1'b0;
      clk40 <= 1'b0;
    end else begin
      if (enb) begin
        if (cnt10 >= 3'd1) begin
          cnt10 <= 3'd0;
          clk10 <= ~clk10;
          if (~clk10) clk20 <= ~clk20;
          if (~clk20 & ~clk10) clk40 <= ~clk40;
        end else begin
          cnt10 <= cnt10 + 1'b1;
        end
      end
    end
  end
endmodule

Modulos/Serial_Paralelo/testSerialParalelo.v
`timescale 1ns/1ps

`include "serialParalelo.v"
`include "GeneradorClk.v"

module testSerialParalelo ();
  reg clk;
  reg enb;
  reg reset;
  reg entrada;
  wire [7:0] salidas;
  wire clk10;
  wire clk20;
  wire clk40;

  GeneradorClk clks(.clk(clk), .rst(reset), .enb(enb), .clk10(clk10), .clk20(clk20), .clk40(clk40));
  serialParalelo prueba(.clk(clk), .reset(reset), .enb(enb), .clk10(clk10), .entrada(entrada), .salidas(salidas));

  always # 4 clk = ~clk;

  initial begin
    $dumpfile("gtkws/testSerPar.vcd");
    $dumpvars;
  end

  initial begin
    clk <= 0;
    reset <= 1'b1;
    enb <= 1;

    # 4
    @ (posedge clk);
    reset <= 1'b0;
    enb <= 1;

    /*
    # 8
    @ (posedge clk);
    entrada <= 1'b0;
    enb <= 1;

    # 8
    @ (posedge clk);
    //entrada <= 1'b0;

    # 8
    @ (posedge clk);
    entrada <= 1'b1;

    //
    // SE APAGA reset
    //
    # 8
    @ (posedge clk);
    reset <= 1'b0;

    */

    // 0110 0110 10
    @ (posedge clk10); entrada <= 1'b0;
    @ (posedge clk); entrada <= 1'b1;
    @ (posedge clk); entrada <= 1'b1;
    @ (posedge clk); entrada <= 1'b0;

    @ (posedge clk); entrada <= 1'b0;
    @ (posedge clk); entrada <= 1'b1;
    @ (posedge clk); entrada <= 1'b1;
    @ (posedge clk); entrada <= 1'b0;


    @ (posedge clk10); entrada <= 1'b1;
    @ (posedge clk); entrada <= 1'b0;
    @ (posedge clk); entrada <= 1'b1;
    @ (posedge clk); entrada <= 1'b0;

    @ (posedge clk); entrada <= 1'b0;
    @ (posedge clk); entrada <= 1'b1;
    @ (posedge clk); entrada <= 1'b0;
    @ (posedge clk); entrada <= 1'b1;


    @ (posedge clk10); entrada <= 1'b1;
    @ (posedge clk); entrada <= 1'b0;
    @ (posedge clk); entrada <= 1'b0;
    @ (posedge clk); entrada <= 1'b0;

    @ (posedge clk); entrada <= 1'b0;
    @ (posedge clk); entrada <= 1'b0;
    @ (posedge clk); entrada <= 1'b0;
    @ (posedge clk); entrada <= 1'b0;


    @ (posedge clk10); entrada <= 1'b0;
    @ (posedge clk); entrada <= 1'b1;
    @ (posedge clk); entrada <= 1'b1;
    @ (posedge clk); entrada <= 1'b1;

    @ (posedge clk); entrada <= 1'b1;
    @ (posedge clk); entrada <= 1'b1;
    @ (posedge clk); entrada <= 1'b1;
    @ (posedge clk); entrada <= 1'b1;


    @ (posedge clk10);
    reset <= 1'b1;

    # 16
    @ (posedge clk);
    entrada <= 1'b0;

    # 16
    @ (posedge clk);
    entrada <= 1'b1;

    # 16
    @ (posedge clk);
    entrada <= 1'b1;

    # 16
    $finish;
  end
endmodule

Modulos/Serial_Paralelo/gtkws/testSerPar.vcd
$date
	Tue May 29 23:03:18 2018
$end
$version
	Icarus Verilog
$end
$timescale
	1ps
$end
$scope module testSerialParalelo $end
$var wire 1 ! clk10 $end
$var wire 1 " clk20 $end
$var wire 1 # clk40 $end
$var wire 8 $ salidas [7:0] $end
$var reg 1 % clk $end
$var reg 1 & enb $end
$var reg 1 ' entrada $end
$var reg 1 ( reset $end
$scope module clks $end
$var wire 1 ) clk $end
$var wire 1 * enb $end
$var wire 1 + rst $end
$var reg 1 , clk10 $end
$var reg 1 - clk20 $end
$var reg 1 . clk40 $end
$var reg 3 / cnt10 [2:0] $end
$upscope $end
$scope module prueba $end
$var wire 1 ) clk $end
$var wire 1 ! clk10 $end
$var wire 1 * enb $end
$var wire 1 0 entrada $end
$var wire 1 + reset $end
$var reg 8 1 bits [7:0] $end
$var reg 4 2 contador [3:0] $end
$var reg 8 3 salidas [7:0] $end
$upscope $end
$upscope $end
$enddefinitions $end
#0
$dumpvars
bx 3
bx 2
bx 1
x0
bx /
x.
x-
x,
1+
1*
0)
1(
x'
1&
0%
bx $
x#
x"
x!
$end
#4000
0.
0#
0-
0"
0,
0!
b100 /
b0 2
1%
1)
#8000
0%
0)
#12000
0(
0+
1%
1)
#16000
0%
0)
#20000
0'
00
1.
1#
1-
1"
1,
1!
b0 /
bx 1
b111 2
1%
1)
#24000
0%
0)
#28000
b0xxxxxxx 1
b110 2
b1 /
1'
10
1%
1)
#32000
0%
0)
#36000
b10 /
b1xxxxxx 1
b101 2
1%
1)
#40000
0%
0)
#44000
b11xxxxx 1
b100 2
b11 /
0'
00
1%
1)
#48000
0%
0)
#52000
b100 /
b110xxxx 1
b11 2
1%
1)
#56000
0%
0)
#60000
b1100xxx 1
b10 2
0,
0!
b0 /
1'
10
1%
1)
#64000
0%
0)
#68000
b1 /
b11001xx 1
b1 2
1%
1)
#72000
0%
0)
#76000
b110011x 1
b0 2
b10 /
0'
00
1%
1)
#80000
0%
0)
#84000
b11 /
b1100110 3
b1100110 $
b1100110 1
b111 2
1%
1)
#88000
0%
0)
#92000
b1100110 1
b110 2
b100 /
1%
1)
#96000
0%
0)
#100000
1'
10
0-
0"
1,
1!
b0 /
b100110 1
b101 2
1%
1)
#104000
0%
0)
#108000
b100110 1
b100 2
b1 /
0'
00
1%
1)
#112000
0%
0)
#116000
1'
10
b10 /
b100110 1
b11 2
1%
1)
#120000
0%
0)
#124000
b101110 1
b10 2
b11 /
0'
00
1%
1)
#128000
0%
0)
#132000
b100 /
b101010 1
b1 2
1%
1)
#136000
0%
0)
#140000
b101000 1
b0 2
0,
0!
b0 /
1'
10
1%
1)
#144000
0%
0)
#148000
0'
00
b1 /
b101001 3
b101001 $
b101001 1
b111 2
1%
1)
#152000
0%
0)
#156000
b101001 1
b110 2
b10 /
1'
10
1%
1)
#160000
0%
0)
#164000
b11 /
b1101001 1
b101 2
1%
1)
#168000
0%
0)
#172000
b1101001 1
b100 2
b100 /
1%
1)
#176000
0%
0)
#180000
0.
0#
1-
1"
1,
1!
b0 /
b1111001 1
b11 2
1%
1)
#184000
0%
0)
#188000
b1111001 1
b10 2
b1 /
0'
00
1%
1)
#192000
0%
0)
#196000
b10 /
b1111001 1
b1 2
1%
1)
#200000
0%
0)
#204000
b1111001 1
b0 2
b11 /
1%
1)
#208000
0%
0)
#212000
b100 /
b1111000 3
b1111000 $
b1111000 1
b111 2
1%
1)
#216000
0%
0)
#220000
b1111000 1
b110 2
0,
0!
b0 /
1%
1)
#224000
0%
0)
#228000
b1 /
b111000 1
b101 2
1%
1)
#232000
0%
0)
#236000
b11000 1
b100 2
b10 /
1%
1)
#240000
0%
0)
#244000
b11 /
b1000 1
b11 2
1%
1)
#248000
0%
0)
#252000
b0 1
b10 2
b100 /
1%
1)
#256000
0%
0)
#260000
0-
0"
1,
1!
b0 /
b0 1
b1 2
1%
1)
#264000
0%
0)
#268000
b0 1
b0 2
b1 /
1'
10
1%
1)
#272000
0%
0)
#276000
b10 /
b1 3
b1 $
b1 1
b111 2
1%
1)
#280000
0%
0)
#284000
b10000001 1
b110 2
b11 /
1%
1)
#288000
0%
0)
#292000
b100 /
b11000001 1
b101 2
1%
1)
#296000
0%
0)
#300000
b11100001 1
b100 2
0,
0!
b0 /
1%
1)
#304000
0%
0)
#308000
b1 /
b11110001 1
b11 2
1%
1)
#312000
0%
0)
#316000
b11111001 1
b10 2
b10 /
1%
1)
#320000
0%
0)
#324000
b11 /
b11111101 1
b1 2
1%
1)
#328000
0%
0)
#332000
b11111111 1
b0 2
b100 /
1%
1)
#336000
0%
0)
#340000
1(
1+
1.
1#
1-
1"
1,
1!
b0 /
b11111111 3
b11111111 $
b11111111 1
b111 2
1%
1)
#344000
0%
0)
#348000
b0 2
0.
0#
0-
0"
0,
0!
b100 /
1%
1)
#352000
0%
0)
#356000
0'
00
1%
1)
#360000
0%
0)
#364000
1%
1)
#368000
0%
0)
#372000
1'
10
1%
1)
