Modulos/ByteUnStriping/unstriping.v
`timescale 1ns/1ps

module unstriping (clk, FL0, FL1, FL2, FL3, toDemux);
    input clk;
    input [7:0] FL0; //FromeLane 0
    input [7:0] FL1; //FromeLane 1
    input [7:0] FL2; //FromeLane 2
    input [7:0] FL3; //FromeLane 3

    output [7:0] toDemux;

    reg [7:0] toDemux;

    reg [1:0] c; //Contador para ver que lane se debe usar
    reg D; // D=0 => no estamos transmitiendo datos || D=1 => estamos transmitiendo datos


    parameter COM = 8'hBC,PAD = 8'hF7,SKP = 8'h1C,STP = 8'hFB, SDP = 8'h5C ;
    parameter END = 8'hFD,EDB = 8'hFE,FTS = 8'h3C,IDL = 8'h7C;

    always @ (posedge clk) begin
      if (D) begin
        if (FL3 == END) begin
          toDemux = FL3;
          D=0;
          c=2'b00;
        end else begin
          if (c==2'b00) begin
                toDemux=FL0;
                c = c+1;
            end else if (c==2'b01) begin
                toDemux=FL1;
                c = c+1;
                
            end else if (c==2'b10) begin
                toDemux=FL2;
                c = c+1;
                
            end else if (c==2'b11) begin
                toDemux = FL3;
                c = c+1;
                end  
        end
      end else begin
        if (FL0 == STP) begin
          D=1;
          toDemux = FL0;
          c = 2'b01;
        end
        if (FL0 == SDP) begin
          D=1;
          toDemux = FL0;
          c = 2'b01;
        end
      end
    end
endmodule

Modulos/ByteUnStriping/TBunstriping.v

`include "unstriping.v"

module TBunstriping;
    reg clk;

    reg [7:0] FL0;
    reg [7:0] FL1;
    reg [7:0] FL2;
    reg [7:0] FL3;

    wire [7:0] toDemux;
    parameter COM = 8'hBC,PAD = 8'hF7,SKP = 8'h1C,STP = 8'hFB, SDP = 8'h5C ;
    parameter END = 8'hFD,EDB = 8'hFE,FTS = 8'h3C,IDL = 8'h7C;

    unstriping unst1 (.clk(clk), .FL0(FL0), .FL1(FL1), .FL2(FL2),.FL3(FL3),.toDemux(toDemux));
    always #1 clk = !clk; //clk sgl.

    initial begin
    $dumpvars;    
    $display ("time\t    clk,    TL0   ,    TL1   ,   TL2   ,   TL3  , tomux ");
    $monitor ("%g\t      %b       %h         %h        %h       %h       %h",
    $time, clk, FL0, FL1, FL2,FL3, toDemux);
    $display ("Se prueba la secuencia:");
    $display ("START(STP = FB)");
    $display ("DATOS(ff)");
    $display ("DATOS(ff)");
    $display ("END(fd)");
    $display ("-------------------");
    
    clk<=0;
    FL0 = STP;
    #2
    FL1 = 8'hFF;
    #2
    FL2 = 8'hFF;
    #2
    FL3 = END;
    #2
    $finish;
    end
    endmodule

Modulos/ByteUnStriping/dump.vcd
$date
	Wed May 30 00:55:21 2018
$end
$version
	Icarus Verilog
$end
$timescale
	1ps
$end
$scope module TBunstriping $end
$var wire 8 ! toDemux [7:0] $end
$var reg 8 " FL0 [7:0] $end
$var reg 8 # FL1 [7:0] $end
$var reg 8 $ FL2 [7:0] $end
$var reg 8 % FL3 [7:0] $end
$var reg 1 & clk $end
$scope module unst1 $end
$var wire 8 ' FL0 [7:0] $end
$var wire 8 ( FL1 [7:0] $end
$var wire 8 ) FL2 [7:0] $end
$var wire 8 * FL3 [7:0] $end
$var wire 1 & clk $end
$var reg 1 + D $end
$var reg 2 , c [1:0] $end
$var reg 8 - toDemux [7:0] $end
$upscope $end
$upscope $end
$enddefinitions $end
#0
$dumpvars
bx -
bx ,
x+
bx *
bx )
bx (
b11111011 '
0&
bx %
bx $
bx #
b11111011 "
bx !
$end
#1000
b1 ,
b11111011 !
b11111011 -
1+
1&
#2000
0&
b11111111 #
b11111111 (
#3000
b10 ,
b11111111 !
b11111111 -
1&
#4000
0&
b11111111 $
b11111111 )
#5000
b11 ,
1&
#6000
0&
b11111101 %
b11111101 *
#7000
b0 ,
0+
b11111101 !
b11111101 -
1&
