Modulos/Tx/ParaleloSerial.v
`timescale 1ns/1ps


module ParaleloSerial(
  clk, reset, enb,
  clk8,
  entrada,
  salida
);

parameter cantBits = 8;

input wire clk;
input wire enb;
input wire reset;
input wire clk8;
input wire [7:0] entrada;
output reg salida;
reg [3:0] contador;

always @ ( * ) begin
salida = ~reset & enb ? entrada[contador] : 0;
end

always @(posedge clk) begin

  if (reset) begin
    contador <= 0;
  end else if(enb) begin
    contador <= contador == 0 ? cantBits-1 : contador-1;
  end
  else  contador = contador;
  end


endmodule

Modulos/Tx/striping.v
`timescale 1ns/1ps

module striping (clk, fromMux, TL0, TL1, TL2,TL3);
input clk;
input [7:0] fromMux;

output [7:0] TL0;
output [7:0] TL1;
output [7:0] TL2;
output [7:0] TL3;

reg [7:0] TL0;
reg [7:0] TL1;
reg [7:0] TL2;
reg [7:0] TL3;

reg [1:0] c; //Contador para ver que lane se debe usar

reg D; // D=0 => no estamos transmitiendo datos || D=1 => estamos transmitiendo datos


parameter COM = 8'hBC,PAD = 8'hF7,SKP = 8'h1C,STP = 8'hFB, SDP = 8'h5C ;
parameter END = 8'hFD,EDB = 8'hFE,FTS = 8'h3C,IDL = 8'h7C;

//D <= 1'b0; 

always @ (posedge clk) begin
      if (D) begin
            if (fromMux == END) begin
            TL3 = fromMux;
            D=0;
            c = 2'b00;
            end else begin
                  if (c==2'b00) begin
                        TL0 = fromMux;
                        c = c+1;
                  end else if (c==2'b01) begin
                        TL1 = fromMux;
                        c = c+1;
                        
                  end else if (c==2'b10) begin
                        TL2 = fromMux;
                        c = c+1;
                        
                  end else if (c==2'b11) begin
                        TL3 = fromMux;
                        c = c+1;
                        end  
            end //end else de            
      end else begin
      
            if (fromMux == STP) begin
            D=1;
            TL0 = fromMux;
            c = 2'b01;
            end  
            if (fromMux == SDP) begin
            D=1;
            TL0 = fromMux;
            c = c+1;
            end

            if (fromMux == IDL) begin
            c = 2'b00;
            TL0 = fromMux;
            TL1 = fromMux;
            TL2 = fromMux;
            TL3 = fromMux;
            end

            if (fromMux == COM) begin
            c = 2'b00;
            TL0 = fromMux;
            TL1 = fromMux;
            TL2 = fromMux;
            TL3 = fromMux;
            end


            if (fromMux == SKP) begin
            c = 2'b00;
            TL0 = fromMux;
            TL1 = fromMux;
            TL2 = fromMux;
            TL3 = fromMux;
            end
      end  //else de if (D)



end //always




      





      /*
      always @ ( * ) begin
      case(fromMux)
      STP : begin
            c = 1'b00; // contador == 00
            if(fromMux=END) begin
                  TL3 = fromMux;
                  end else begin
                  //ACOMODAR LOS BICHOS EN EL LANE CORRESPONDIENTE E INCREMENTAR EL CONTADOR
                  end
                  
            end

      SDP : TL0 = fromMux; //Start

      END : TL3 = fromMux;

      //EDB : TL3 = fromMux;

      SKP : begin
            TL0 = fromMux;
            TL1 = fromMux;
            TL2 = fromMux;
            TL3 = fromMux;
            end
      
      IDL : begin
            c = 1'b00;
            TL0 = fromMux;
            TL1 = fromMux;
            TL2 = fromMux;
            TL3 = fromMux;
            end
      


      end

      */

endmodule


      /*
      -value en 1, y selec de mux para que mande IDLE

      -Start-Datoooooos-End, Verificar multiplos de 4 bytes para que el END quede en el ultimo
      Mandar datos por multiplos de 4 bytes, contando Start y END



      */

Modulos/Mux_Ctrl/MuxCtrl.v
module MuxCtrl(

input clk,
input [7:0] data,
input enb,
input [3:0] S,
output [7:0] outmux

);

reg outmux;

parameter COM = 8'hBC,PAD = 8'hF7,SKP = 8'h1C,STP = 8'hFB, SDP = 8'h5C ;
parameter END = 8'hFD,EDB = 8'hFE,FTS = 8'h3C,IDL = 8'h7C;

always @ (posedge clk)
  begin
    if (enb) begin
      case(S)
        4'b0000 : outmux = data;

        4'b0001 : outmux = COM;

        4'b0010 : outmux = PAD;

        4'b0011 : outmux = SKP;

        4'b0100 : outmux = STP;

        4'b0101 : outmux = SDP;

        4'b0110 : outmux = END;

        4'b0111 : outmux = EDB;

        4'b1000 : outmux = FTS;

        4'b1001 : outmux = IDL;
      endcase
    end
  end
  endmodule

Modulos/Tx/Tx.v
`timescale 1ns/1ps

`include "MuxCtrl.v"
`include "striping.v"
`include "ParaleloSerial.v"

module Tx (clk, clk2, data, enb, reset, S, L0, L1, L2, L3);
  input clk;
  input clk2;
  input [7:0] data;
  input enb;
  input reset;
  input [3:0] S;

  output L0;
  output L1;
  output L2;
  output L3;

  wire [7:0] outmux;

  wire [7:0] TL0;
  wire [7:0] TL1;
  wire [7:0] TL2;
  wire [7:0] TL3;

  MuxCtrl Mux1(.clk(clk), .data(data), .enb(enb), .S(S), .outmux(outmux));

  striping byteStp (.clk(clk), .fromMux(outmux), .TL0(TL0), .TL1(TL1), .TL2(TL2),.TL3(TL3));

  ParaleloSerial PS0 (.clk(clk2), .reset(reset), .enb(enb), .clk8(clk), .entrada(TL0), .salida(L0));
  ParaleloSerial PS1 (.clk(clk2), .reset(reset), .enb(enb), .clk8(clk), .entrada(TL1), .salida(L1));
  ParaleloSerial PS2 (.clk(clk2), .reset(reset), .enb(enb), .clk8(clk), .entrada(TL2), .salida(L2));
  ParaleloSerial PS3 (.clk(clk2), .reset(reset), .enb(enb), .clk8(clk), .entrada(TL3), .salida(L3));
endmodule

Modulos/Rx/GeneradorClk.v
`timescale 1ns/1ps

module GeneradorClk(
  clk, rst, enb,
  clk10, clk20, clk40
);


  input wire clk;
  input wire rst;
  input wire enb;

  output reg clk10;
  output reg clk20;
  output reg clk40;

  reg [2:0] cnt10;

  always @ (posedge clk) begin
    if (rst) begin
      cnt10 <= 3'd1;
      clk10 <= 1'b0;
      clk20 <= 1'b0;
      clk40 <= 1'b0;
    end else begin
      if (enb) begin
        if (cnt10 >= 3'd1) begin
          cnt10 <= 3'd0;
          clk10 <= ~clk10;
          if (~clk10) clk20 <= ~clk20;
          if (~clk20 & ~clk10) clk40 <= ~clk40;
        end else begin
          cnt10 <= cnt10 + 1'b1;
        end
      end
    end
  end
endmodule

Modulos/Tx/TBtx.v
`timescale 1ns/1ps

`include "Tx.v"
`include "GeneradorClk.v"


module TB();
    reg clk;
    reg clk2;
    reg [7:0] data;
    reg enb;
    reg reset;
    reg [3:0] S;


    wire clk10;
    wire clk20;
    wire clk40;

    wire L0;
    wire L1;
    wire L2;
    wire L3;


    GeneradorClk clks(.clk(clk), .rst(reset), .enb(enb), .clk10(clk10), .clk20(clk20), .clk40(clk40));
    Tx prueba(.clk(clk10), .clk2(clk), .data(data), .enb(enb), .reset(reset), .S(S), .L0(L0), .L1(L1), .L2(L2), .L3(L3));

    always #4 clk = !clk; //clk sgl.
    always #1 clk2 = !clk2; //clk sgl.

    initial begin
    $display ("test");
    $dumpfile("gtkws/testTx.vcd");
    $dumpvars;
    $display ("time\t    clk  ,   clk10  , data  ,   enb  ,   S   ,   L0  ,   L1  ,   L2  ,   L3 ");
    $monitor ("%g\t      %b        %b      %h       %b      %b        %b       %b       %b      %b",
    $time, clk, clk10, data, enb, S, L0, L1, L2, L3);

    clk <= 1;
    clk2 <=1;
    reset <= 1'b1;
    enb <= 0;
    S <=4'b1001;

    # 4
    @ (posedge clk);
    reset <= 1'b0;
    enb <= 1;


    # 4
        $display("inicio");

    @ (posedge clk10);
    data <= 8'b11100110;
    S <=4'b0100;
    # 64
    @ (posedge clk10);
    data <= 8'b00001101;
    S <=4'b0000;
    # 64
    @ (posedge clk10);
    data <= 8'b01011101;
    S <=4'b0110;
    # 64

    $finish;
    end
  endmodule

Modulos/Tx/gtkws/testTx.vcd
$date
	Wed May 30 07:41:29 2018
$end
$version
	Icarus Verilog
$end
$timescale
	1ps
$end
$scope module TB $end
$var wire 1 ! L0 $end
$var wire 1 " L1 $end
$var wire 1 # L2 $end
$var wire 1 $ L3 $end
$var wire 1 % clk10 $end
$var wire 1 & clk20 $end
$var wire 1 ' clk40 $end
$var reg 4 ( S [3:0] $end
$var reg 1 ) clk $end
$var reg 1 * clk2 $end
$var reg 8 + data [7:0] $end
$var reg 1 , enb $end
$var reg 1 - reset $end
$scope module clks $end
$var wire 1 . clk $end
$var wire 1 / enb $end
$var wire 1 0 rst $end
$var reg 1 1 clk10 $end
$var reg 1 2 clk20 $end
$var reg 1 3 clk40 $end
$var reg 3 4 cnt10 [2:0] $end
$upscope $end
$scope module prueba $end
$var wire 1 ! L0 $end
$var wire 1 " L1 $end
$var wire 1 # L2 $end
$var wire 1 $ L3 $end
$var wire 4 5 S [3:0] $end
$var wire 8 6 TL0 [7:0] $end
$var wire 8 7 TL1 [7:0] $end
$var wire 8 8 TL2 [7:0] $end
$var wire 8 9 TL3 [7:0] $end
$var wire 1 % clk $end
$var wire 1 . clk2 $end
$var wire 8 : data [7:0] $end
$var wire 1 / enb $end
$var wire 8 ; outmux [7:0] $end
$var wire 1 0 reset $end
$scope module Mux1 $end
$var wire 4 < S [3:0] $end
$var wire 1 % clk $end
$var wire 8 = data [7:0] $end
$var wire 1 / enb $end
$var reg 8 > outmux [7:0] $end
$upscope $end
$scope module byteStp $end
$var wire 1 % clk $end
$var wire 8 ? fromMux [7:0] $end
$var reg 1 @ D $end
$var reg 8 A TL0 [7:0] $end
$var reg 8 B TL1 [7:0] $end
$var reg 8 C TL2 [7:0] $end
$var reg 8 D TL3 [7:0] $end
$var reg 2 E c [1:0] $end
$upscope $end
$scope module PS0 $end
$var wire 1 . clk $end
$var wire 1 % clk8 $end
$var wire 1 / enb $end
$var wire 8 F entrada [7:0] $end
$var wire 1 0 reset $end
$var reg 4 G contador [3:0] $end
$var reg 1 H salida $end
$upscope $end
$scope module PS1 $end
$var wire 1 . clk $end
$var wire 1 % clk8 $end
$var wire 1 / enb $end
$var wire 8 I entrada [7:0] $end
$var wire 1 0 reset $end
$var reg 4 J contador [3:0] $end
$var reg 1 K salida $end
$upscope $end
$scope module PS2 $end
$var wire 1 . clk $end
$var wire 1 % clk8 $end
$var wire 1 / enb $end
$var wire 8 L entrada [7:0] $end
$var wire 1 0 reset $end
$var reg 4 M contador [3:0] $end
$var reg 1 N salida $end
$upscope $end
$scope module PS3 $end
$var wire 1 . clk $end
$var wire 1 % clk8 $end
$var wire 1 / enb $end
$var wire 8 O entrada [7:0] $end
$var wire 1 0 reset $end
$var reg 4 P contador [3:0] $end
$var reg 1 Q salida $end
$upscope $end
$upscope $end
$upscope $end
$enddefinitions $end
#0
$dumpvars
0Q
b0 P
bx O
0N
b0 M
bx L
0K
b0 J
bx I
0H
b0 G
bx F
bx E
bx D
bx C
bx B
bx A
x@
bx ?
bx >
bx =
b1001 <
bx ;
bx :
bx 9
bx 8
bx 7
bx 6
b1001 5
b11 4
03
02
01
10
0/
1.
1-
0,
bx +
1*
1)
b1001 (
0'
0&
0%
0$
0#
0"
0!
$end
#1000
0*
#2000
1*
#3000
0*
#4000
1*
0)
0.
#5000
0*
#6000
1*
#7000
0*
#8000
xQ
x$
xN
x#
xK
x"
xH
x!
1,
1/
0-
00
1*
1)
1.
#9000
0*
#10000
1*
#11000
0*
#12000
1*
0)
0.
#13000
0*
#14000
1*
#15000
0*
#16000
b100 (
b100 5
b100 <
b11100110 +
b11100110 :
b11100110 =
b1111100 >
b1111100 ;
b1111100 ?
13
1'
12
1&
11
1%
b0 4
b111 G
b111 J
b111 M
b111 P
1*
1)
1.
#17000
0*
#18000
1*
#19000
0*
#20000
1*
0)
0.
#21000
0*
#22000
1*
#23000
0*
#24000
b110 P
b110 M
b110 J
b110 G
b1 4
1*
1)
1.
#25000
0*
#26000
1*
#27000
0*
#28000
1*
0)
0.
#29000
0*
#30000
1*
#31000
0*
#32000
b10 4
b101 G
b101 J
b101 M
b101 P
1*
1)
1.
#33000
0*
#34000
1*
#35000
0*
#36000
1*
0)
0.
#37000
0*
#38000
1*
#39000
0*
#40000
b100 P
b100 M
b100 J
b100 G
b11 4
1*
1)
1.
#41000
0*
#42000
1*
#43000
0*
#44000
1*
0)
0.
#45000
0*
#46000
1*
#47000
0*
#48000
01
0%
b0 4
b11 G
b11 J
b11 M
b11 P
1*
1)
1.
#49000
0*
#50000
1*
#51000
0*
#52000
1*
0)
0.
#53000
0*
#54000
1*
#55000
0*
#56000
b10 P
b10 M
b10 J
b10 G
b1 4
1*
1)
1.
#57000
0*
#58000
1*
#59000
0*
#60000
1*
0)
0.
#61000
0*
#62000
1*
#63000
0*
#64000
b10 4
b1 G
b1 J
b1 M
b1 P
1*
1)
1.
#65000
0*
#66000
1*
#67000
0*
#68000
1*
0)
0.
#69000
0*
#70000
1*
#71000
0*
#72000
b0 P
b0 M
b0 J
b0 G
b11 4
1*
1)
1.
#73000
0*
#74000
1*
#75000
0*
#76000
1*
0)
0.
#77000
0*
#78000
1*
#79000
0*
#80000
b0 (
b0 5
b0 <
b1101 +
b1101 :
b1101 =
1H
1!
b1 E
b11111011 A
b11111011 6
b11111011 F
1@
b11111011 >
b11111011 ;
b11111011 ?
02
0&
11
1%
b0 4
b111 G
b111 J
b111 M
b111 P
1*
1)
1.
#81000
0*
#82000
1*
#83000
0*
#84000
1*
0)
0.
#85000
0*
#86000
1*
#87000
0*
#88000
b110 P
b110 M
b110 J
b110 G
b1 4
1*
1)
1.
#89000
0*
#90000
1*
#91000
0*
#92000
1*
0)
0.
#93000
0*
#94000
1*
#95000
0*
#96000
b10 4
b101 G
b101 J
b101 M
b101 P
1*
1)
1.
#97000
0*
#98000
1*
#99000
0*
#100000
1*
0)
0.
#101000
0*
#102000
1*
#103000
0*
#104000
b100 P
b100 M
b100 J
b100 G
b11 4
1*
1)
1.
#105000
0*
#106000
1*
#107000
0*
#108000
1*
0)
0.
#109000
0*
#110000
1*
#111000
0*
#112000
01
0%
b0 4
b11 G
b11 J
b11 M
b11 P
1*
1)
1.
#113000
0*
#114000
1*
#115000
0*
#116000
1*
0)
0.
#117000
0*
#118000
1*
#119000
0*
#120000
0H
0!
b10 P
b10 M
b10 J
b10 G
b1 4
1*
1)
1.
#121000
0*
#122000
1*
#123000
0*
#124000
1*
0)
0.
#125000
0*
#126000
1*
#127000
0*
#128000
1H
1!
b10 4
b1 G
b1 J
b1 M
b1 P
1*
1)
1.
#129000
0*
#130000
1*
#131000
0*
#132000
1*
0)
0.
#133000
0*
#134000
1*
#135000
0*
#136000
b0 P
b0 M
b0 J
b0 G
b11 4
1*
1)
1.
#137000
0*
#138000
1*
#139000
0*
#140000
1*
0)
0.
#141000
0*
#142000
1*
#143000
0*
#144000
b110 (
b110 5
b110 <
b1011101 +
b1011101 :
b1011101 =
1K
1"
b1101 >
b1101 ;
b1101 ?
b10 E
b11111011 B
b11111011 7
b11111011 I
03
0'
12
1&
11
1%
b0 4
b111 G
b111 J
b111 M
b111 P
1*
1)
1.
#145000
0*
#146000
1*
#147000
0*
#148000
1*
0)
0.
#149000
0*
#150000
1*
#151000
0*
#152000
b110 P
b110 M
b110 J
b110 G
b1 4
1*
1)
1.
#153000
0*
#154000
1*
#155000
0*
#156000
1*
0)
0.
#157000
0*
#158000
1*
#159000
0*
#160000
b10 4
b101 G
b101 J
b101 M
b101 P
1*
1)
1.
#161000
0*
#162000
1*
#163000
0*
#164000
1*
0)
0.
#165000
0*
#166000
1*
#167000
0*
#168000
b100 P
b100 M
b100 J
b100 G
b11 4
1*
1)
1.
#169000
0*
#170000
1*
#171000
0*
#172000
1*
0)
0.
#173000
0*
#174000
1*
#175000
0*
#176000
01
0%
b0 4
b11 G
b11 J
b11 M
b11 P
1*
1)
1.
#177000
0*
#178000
1*
#179000
0*
#180000
1*
0)
0.
#181000
0*
#182000
1*
#183000
0*
#184000
0K
0"
0H
0!
b10 P
b10 M
b10 J
b10 G
b1 4
1*
1)
1.
#185000
0*
#186000
1*
#187000
0*
#188000
1*
0)
0.
#189000
0*
#190000
1*
#191000
0*
#192000
1H
1!
1K
1"
b10 4
b1 G
b1 J
b1 M
b1 P
1*
1)
1.
#193000
0*
#194000
1*
#195000
0*
#196000
1*
0)
0.
#197000
0*
#198000
1*
#199000
0*
#200000
b0 P
b0 M
b0 J
b0 G
b11 4
1*
1)
1.
#201000
0*
#202000
1*
#203000
0*
#204000
1*
0)
0.
#205000
0*
#206000
1*
#207000
0*
#208000
1Q
1$
b0 E
0@
b11111101 D
b11111101 9
b11111101 O
b11111101 >
b11111101 ;
b11111101 ?
02
0&
11
1%
b0 4
b111 G
b111 J
b111 M
b111 P
1*
1)
1.
