Modulos/Tx/ParaleloSerial.v
`timescale 1ns/1ps


module ParaleloSerial(
  clk, reset, enb,
  clk8,
  entrada,
  salida
);

parameter cantBits = 8;

input wire clk;
input wire enb;
input wire reset;
input wire clk8;
input wire [7:0] entrada;
output reg salida;
reg [3:0] contador;

always @ ( * ) begin
salida = ~reset & enb ? entrada[contador] : 0;
end

always @(posedge clk) begin

  if (reset) begin
    contador <= 0;
  end else if(enb) begin
    contador <= contador == 0 ? cantBits-1 : contador-1;
  end
  else  contador = contador;
  end


endmodule

Modulos/Tx/striping.v
`timescale 1ns/1ps

module striping (clk, fromMux, TL0, TL1, TL2,TL3);
input clk;
input [7:0] fromMux;

output [7:0] TL0;
output [7:0] TL1;
output [7:0] TL2;
output [7:0] TL3;

reg [7:0] TL0;
reg [7:0] TL1;
reg [7:0] TL2;
reg [7:0] TL3;

reg [1:0] c; //Contador para ver que lane se debe usar

reg D; // D=0 => no estamos transmitiendo datos || D=1 => estamos transmitiendo datos


parameter COM = 8'hBC,PAD = 8'hF7,SKP = 8'h1C,STP = 8'hFB, SDP = 8'h5C ;
parameter END = 8'hFD,EDB = 8'hFE,FTS = 8'h3C,IDL = 8'h7C;

//D <= 1'b0; 

always @ (posedge clk) begin
      if (D) begin
            if (fromMux == END) begin
            TL3 = fromMux;
            D=0;
            c = 2'b00;
            end else begin
                  if (c==2'b00) begin
                        TL0 = fromMux;
                        c = c+1;
                  end else if (c==2'b01) begin
                        TL1 = fromMux;
                        c = c+1;
                        
                  end else if (c==2'b10) begin
                        TL2 = fromMux;
                        c = c+1;
                        
                  end else if (c==2'b11) begin
                        TL3 = fromMux;
                        c = c+1;
                        end  
            end //end else de            
      end else begin
      
            if (fromMux == STP) begin
            D=1;
            TL0 = fromMux;
            c = 2'b01;
            end  
            if (fromMux == SDP) begin
            D=1;
            TL0 = fromMux;
            c = c+1;
            end

            if (fromMux == IDL) begin
            c = 2'b00;
            TL0 = fromMux;
            TL1 = fromMux;
            TL2 = fromMux;
            TL3 = fromMux;
            end

            if (fromMux == COM) begin
            c = 2'b00;
            TL0 = fromMux;
            TL1 = fromMux;
            TL2 = fromMux;
            TL3 = fromMux;
            end


            if (fromMux == SKP) begin
            c = 2'b00;
            TL0 = fromMux;
            TL1 = fromMux;
            TL2 = fromMux;
            TL3 = fromMux;
            end
      end  //else de if (D)



end //always




      





      /*
      always @ ( * ) begin
      case(fromMux)
      STP : begin
            c = 1'b00; // contador == 00
            if(fromMux=END) begin
                  TL3 = fromMux;
                  end else begin
                  //ACOMODAR LOS BICHOS EN EL LANE CORRESPONDIENTE E INCREMENTAR EL CONTADOR
                  end
                  
            end

      SDP : TL0 = fromMux; //Start

      END : TL3 = fromMux;

      //EDB : TL3 = fromMux;

      SKP : begin
            TL0 = fromMux;
            TL1 = fromMux;
            TL2 = fromMux;
            TL3 = fromMux;
            end
      
      IDL : begin
            c = 1'b00;
            TL0 = fromMux;
            TL1 = fromMux;
            TL2 = fromMux;
            TL3 = fromMux;
            end
      


      end

      */

endmodule


      /*
      -value en 1, y selec de mux para que mande IDLE

      -Start-Datoooooos-End, Verificar multiplos de 4 bytes para que el END quede en el ultimo
      Mandar datos por multiplos de 4 bytes, contando Start y END



      */

Modulos/Mux_Ctrl/MuxCtrl.v
module MuxCtrl(

input clk,
input [7:0] data,
input enb,
input [3:0] S,
output [7:0] outmux

);

reg outmux;

parameter COM = 8'hBC,PAD = 8'hF7,SKP = 8'h1C,STP = 8'hFB, SDP = 8'h5C ;
parameter END = 8'hFD,EDB = 8'hFE,FTS = 8'h3C,IDL = 8'h7C;

always @ (posedge clk)
  begin
    if (enb) begin
      case(S)
        4'b0000 : outmux = data;

        4'b0001 : outmux = COM;

        4'b0010 : outmux = PAD;

        4'b0011 : outmux = SKP;

        4'b0100 : outmux = STP;

        4'b0101 : outmux = SDP;

        4'b0110 : outmux = END;

        4'b0111 : outmux = EDB;

        4'b1000 : outmux = FTS;

        4'b1001 : outmux = IDL;
      endcase
    end
  end
  endmodule

Modulos/Tx/Tx.v
`timescale 1ns/1ps

`include "MuxCtrl.v"
`include "striping.v"
`include "ParaleloSerial.v"

module Tx (clk, clk2, data, enb, reset, S, L0, L1, L2, L3);
  input clk;
  input clk2;
  input [7:0] data;
  input enb;
  input reset;
  input [3:0] S;

  output L0;
  output L1;
  output L2;
  output L3;

  wire [7:0] outmux;

  wire [7:0] TL0;
  wire [7:0] TL1;
  wire [7:0] TL2;
  wire [7:0] TL3;

  MuxCtrl Mux1(.clk(clk), .data(data), .enb(enb), .S(S), .outmux(outmux));

  striping byteStp (.clk(clk), .fromMux(outmux), .TL0(TL0), .TL1(TL1), .TL2(TL2),.TL3(TL3));

  ParaleloSerial PS0 (.clk(clk2), .reset(reset), .enb(enb), .clk8(clk), .entrada(TL0), .salida(L0));
  ParaleloSerial PS1 (.clk(clk2), .reset(reset), .enb(enb), .clk8(clk), .entrada(TL1), .salida(L1));
  ParaleloSerial PS2 (.clk(clk2), .reset(reset), .enb(enb), .clk8(clk), .entrada(TL2), .salida(L2));
  ParaleloSerial PS3 (.clk(clk2), .reset(reset), .enb(enb), .clk8(clk), .entrada(TL3), .salida(L3));
endmodule

Modulos/Rx/GeneradorClk.v
`timescale 1ns/1ps

module GeneradorClk(
  clk, rst, enb,
  clk10, clk20, clk40
);


  input wire clk;
  input wire rst;
  input wire enb;

  output reg clk10;
  output reg clk20;
  output reg clk40;

  reg [2:0] cnt10;

  always @ (posedge clk) begin
    if (rst) begin
      cnt10 <= 3'd1;
      clk10 <= 1'b0;
      clk20 <= 1'b0;
      clk40 <= 1'b0;
    end else begin
      if (enb) begin
        if (cnt10 >= 3'd1) begin
          cnt10 <= 3'd0;
          clk10 <= ~clk10;
          if (~clk10) clk20 <= ~clk20;
          if (~clk20 & ~clk10) clk40 <= ~clk40;
        end else begin
          cnt10 <= cnt10 + 1'b1;
        end
      end
    end
  end
endmodule

Modulos/Tx/TBtx.v
`timescale 1ns/1ps

`include "Tx.v"
`include "GeneradorClk.v"


module TB();
    reg clk;
    reg clk2;
    reg [7:0] data;
    reg enb;
    reg reset;
    reg [3:0] S;


    wire clk10;
    wire clk20;
    wire clk40;

    wire L0;
    wire L1;
    wire L2;
    wire L3;


    GeneradorClk clks(.clk(clk), .rst(reset), .enb(enb), .clk10(clk10), .clk20(clk20), .clk40(clk40));
    Tx prueba(.clk(clk10), .clk2(clk), .data(data), .enb(enb), .reset(reset), .S(S), .L0(L0), .L1(L1), .L2(L2), .L3(L3));

    always #4 clk = !clk; //clk sgl.
    always #1 clk2 = !clk2; //clk sgl.

    initial begin
    $display ("test");
    $dumpfile("gtkws/testTx.vcd");
    $dumpvars;
    $display ("time\t    clk  ,   clk10  , data  ,   enb  ,   S   ,   L0  ,   L1  ,   L2  ,   L3 ");
    $monitor ("%g\t      %b        %b      %h       %b      %b        %b       %b       %b      %b",
    $time, clk, clk10, data, enb, S, L0, L1, L2, L3);

    clk <= 1;
    clk2 <=1;
    reset <= 1'b1;
    enb <= 0;
    S <=4'b1001;

    # 8
    @ (posedge clk);
    reset <= 1'b0;
    enb <= 1;


    # 8
        $display("inicio");

    @ (posedge clk10);
    //------------------
    #64
    data <= 8'b11100110;
    S <=4'b1001;
    # 64
    #64
    #64
      data <= 8'b11100110;
	    S <=4'b0100;
	    # 64
      data <= 8'h01;
      S <=4'b0000;
      # 64
      data <= 8'h02;
      # 64
      data <= 8'h03;
      # 64
      data <= 8'h04;
      # 64
      data <= 8'h05;
      # 64

//---------------------
    @ (posedge clk10);
    data <= 8'b00001101;
    S <=4'b0000;
    # 64
    @ (posedge clk10);
    data <= 8'b01011101;
    S <=4'b0110;
    # 64

    $finish;
    end
  endmodule

Modulos/Tx/gtkws/testTx.vcd
$date
	Fri Jun  1 18:33:02 2018
$end
$version
	Icarus Verilog
$end
$timescale
	1ps
$end
$scope module TB $end
$var wire 1 ! clk40 $end
$var wire 1 " clk20 $end
$var wire 1 # clk10 $end
$var wire 1 $ L3 $end
$var wire 1 % L2 $end
$var wire 1 & L1 $end
$var wire 1 ' L0 $end
$var reg 4 ( S [3:0] $end
$var reg 1 ) clk $end
$var reg 1 * clk2 $end
$var reg 8 + data [7:0] $end
$var reg 1 , enb $end
$var reg 1 - reset $end
$scope module clks $end
$var wire 1 ) clk $end
$var wire 1 , enb $end
$var wire 1 - rst $end
$var reg 1 # clk10 $end
$var reg 1 " clk20 $end
$var reg 1 ! clk40 $end
$var reg 3 . cnt10 [2:0] $end
$upscope $end
$scope module prueba $end
$var wire 4 / S [3:0] $end
$var wire 1 # clk $end
$var wire 1 ) clk2 $end
$var wire 8 0 data [7:0] $end
$var wire 1 , enb $end
$var wire 1 - reset $end
$var wire 8 1 outmux [7:0] $end
$var wire 8 2 TL3 [7:0] $end
$var wire 8 3 TL2 [7:0] $end
$var wire 8 4 TL1 [7:0] $end
$var wire 8 5 TL0 [7:0] $end
$var wire 1 $ L3 $end
$var wire 1 % L2 $end
$var wire 1 & L1 $end
$var wire 1 ' L0 $end
$scope module Mux1 $end
$var wire 4 6 S [3:0] $end
$var wire 1 # clk $end
$var wire 8 7 data [7:0] $end
$var wire 1 , enb $end
$var reg 8 8 outmux [7:0] $end
$upscope $end
$scope module PS0 $end
$var wire 1 ) clk $end
$var wire 1 # clk8 $end
$var wire 1 , enb $end
$var wire 1 - reset $end
$var wire 8 9 entrada [7:0] $end
$var reg 4 : contador [3:0] $end
$var reg 1 ' salida $end
$upscope $end
$scope module PS1 $end
$var wire 1 ) clk $end
$var wire 1 # clk8 $end
$var wire 1 , enb $end
$var wire 1 - reset $end
$var wire 8 ; entrada [7:0] $end
$var reg 4 < contador [3:0] $end
$var reg 1 & salida $end
$upscope $end
$scope module PS2 $end
$var wire 1 ) clk $end
$var wire 1 # clk8 $end
$var wire 1 , enb $end
$var wire 1 - reset $end
$var wire 8 = entrada [7:0] $end
$var reg 4 > contador [3:0] $end
$var reg 1 % salida $end
$upscope $end
$scope module PS3 $end
$var wire 1 ) clk $end
$var wire 1 # clk8 $end
$var wire 1 , enb $end
$var wire 1 - reset $end
$var wire 8 ? entrada [7:0] $end
$var reg 4 @ contador [3:0] $end
$var reg 1 $ salida $end
$upscope $end
$scope module byteStp $end
$var wire 1 # clk $end
$var wire 8 A fromMux [7:0] $end
$var reg 1 B D $end
$var reg 8 C TL0 [7:0] $end
$var reg 8 D TL1 [7:0] $end
$var reg 8 E TL2 [7:0] $end
$var reg 8 F TL3 [7:0] $end
$var reg 2 G c [1:0] $end
$upscope $end
$upscope $end
$upscope $end
$enddefinitions $end
#0
$dumpvars
bx G
bx F
bx E
bx D
bx C
xB
bx A
b0 @
bx ?
b0 >
bx =
b0 <
bx ;
b0 :
bx 9
bx 8
bx 7
b1001 6
bx 5
bx 4
bx 3
bx 2
bx 1
bx 0
b1001 /
b11 .
1-
0,
bx +
1*
1)
b1001 (
0'
0&
0%
0$
0#
0"
0!
$end
#1000
0*
#2000
1*
#3000
0*
#4000
1*
0)
#5000
0*
#6000
1*
#7000
0*
#8000
x'
x&
x%
x$
1,
0-
1*
1)
#9000
0*
#10000
1*
#11000
0*
#12000
1*
0)
#13000
0*
#14000
1*
#15000
0*
#16000
b1111100 1
b1111100 8
b1111100 A
1!
1"
1#
b0 .
b111 :
b111 <
b111 >
b111 @
1*
1)
#17000
0*
#18000
1*
#19000
0*
#20000
1*
0)
#21000
0*
#22000
1*
#23000
0*
#24000
b110 @
b110 >
b110 <
b110 :
b1 .
1*
1)
#25000
0*
#26000
1*
#27000
0*
#28000
1*
0)
#29000
0*
#30000
1*
#31000
0*
#32000
b10 .
b101 :
b101 <
b101 >
b101 @
1*
1)
#33000
0*
#34000
1*
#35000
0*
#36000
1*
0)
#37000
0*
#38000
1*
#39000
0*
#40000
b100 @
b100 >
b100 <
b100 :
b11 .
1*
1)
#41000
0*
#42000
1*
#43000
0*
#44000
1*
0)
#45000
0*
#46000
1*
#47000
0*
#48000
0#
b0 .
b11 :
b11 <
b11 >
b11 @
1*
1)
#49000
0*
#50000
1*
#51000
0*
#52000
1*
0)
#53000
0*
#54000
1*
#55000
0*
#56000
b10 @
b10 >
b10 <
b10 :
b1 .
1*
1)
#57000
0*
#58000
1*
#59000
0*
#60000
1*
0)
#61000
0*
#62000
1*
#63000
0*
#64000
b10 .
b1 :
b1 <
b1 >
b1 @
1*
1)
#65000
0*
#66000
1*
#67000
0*
#68000
1*
0)
#69000
0*
#70000
1*
#71000
0*
#72000
b0 @
b0 >
b0 <
b0 :
b11 .
1*
1)
#73000
0*
#74000
1*
#75000
0*
#76000
1*
0)
#77000
0*
#78000
1*
#79000
0*
#80000
0$
0%
0&
0'
b1111100 2
b1111100 ?
b1111100 F
b1111100 3
b1111100 =
b1111100 E
b1111100 4
b1111100 ;
b1111100 D
b1111100 5
b1111100 9
b1111100 C
b0 G
0"
1#
b0 .
b111 :
b111 <
b111 >
b111 @
b11100110 +
b11100110 0
b11100110 7
1*
1)
#81000
0*
#82000
1*
#83000
0*
#84000
1*
0)
#85000
0*
#86000
1*
#87000
0*
#88000
1$
1%
1&
1'
b110 @
b110 >
b110 <
b110 :
b1 .
1*
1)
#89000
0*
#90000
1*
#91000
0*
#92000
1*
0)
#93000
0*
#94000
1*
#95000
0*
#96000
b10 .
b101 :
b101 <
b101 >
b101 @
1*
1)
#97000
0*
#98000
1*
#99000
0*
#100000
1*
0)
#101000
0*
#102000
1*
#103000
0*
#104000
b100 @
b100 >
b100 <
b100 :
b11 .
1*
1)
#105000
0*
#106000
1*
#107000
0*
#108000
1*
0)
#109000
0*
#110000
1*
#111000
0*
#112000
0#
b0 .
b11 :
b11 <
b11 >
b11 @
1*
1)
#113000
0*
#114000
1*
#115000
0*
#116000
1*
0)
#117000
0*
#118000
1*
#119000
0*
#120000
b10 @
b10 >
b10 <
b10 :
b1 .
1*
1)
#121000
0*
#122000
1*
#123000
0*
#124000
1*
0)
#125000
0*
#126000
1*
#127000
0*
#128000
0'
0&
0%
0$
b10 .
b1 :
b1 <
b1 >
b1 @
1*
1)
#129000
0*
#130000
1*
#131000
0*
#132000
1*
0)
#133000
0*
#134000
1*
#135000
0*
#136000
b0 @
b0 >
b0 <
b0 :
b11 .
1*
1)
#137000
0*
#138000
1*
#139000
0*
#140000
1*
0)
#141000
0*
#142000
1*
#143000
0*
#144000
0!
1"
1#
b0 .
b111 :
b111 <
b111 >
b111 @
1*
1)
#145000
0*
#146000
1*
#147000
0*
#148000
1*
0)
#149000
0*
#150000
1*
#151000
0*
#152000
1$
1%
1&
1'
b110 @
b110 >
b110 <
b110 :
b1 .
1*
1)
#153000
0*
#154000
1*
#155000
0*
#156000
1*
0)
#157000
0*
#158000
1*
#159000
0*
#160000
b10 .
b101 :
b101 <
b101 >
b101 @
1*
1)
#161000
0*
#162000
1*
#163000
0*
#164000
1*
0)
#165000
0*
#166000
1*
#167000
0*
#168000
b100 @
b100 >
b100 <
b100 :
b11 .
1*
1)
#169000
0*
#170000
1*
#171000
0*
#172000
1*
0)
#173000
0*
#174000
1*
#175000
0*
#176000
0#
b0 .
b11 :
b11 <
b11 >
b11 @
1*
1)
#177000
0*
#178000
1*
#179000
0*
#180000
1*
0)
#181000
0*
#182000
1*
#183000
0*
#184000
b10 @
b10 >
b10 <
b10 :
b1 .
1*
1)
#185000
0*
#186000
1*
#187000
0*
#188000
1*
0)
#189000
0*
#190000
1*
#191000
0*
#192000
0'
0&
0%
0$
b10 .
b1 :
b1 <
b1 >
b1 @
1*
1)
#193000
0*
#194000
1*
#195000
0*
#196000
1*
0)
#197000
0*
#198000
1*
#199000
0*
#200000
b0 @
b0 >
b0 <
b0 :
b11 .
1*
1)
#201000
0*
#202000
1*
#203000
0*
#204000
1*
0)
#205000
0*
#206000
1*
#207000
0*
#208000
0"
1#
b0 .
b111 :
b111 <
b111 >
b111 @
1*
1)
#209000
0*
#210000
1*
#211000
0*
#212000
1*
0)
#213000
0*
#214000
1*
#215000
0*
#216000
1$
1%
1&
1'
b110 @
b110 >
b110 <
b110 :
b1 .
1*
1)
#217000
0*
#218000
1*
#219000
0*
#220000
1*
0)
#221000
0*
#222000
1*
#223000
0*
#224000
b10 .
b101 :
b101 <
b101 >
b101 @
1*
1)
#225000
0*
#226000
1*
#227000
0*
#228000
1*
0)
#229000
0*
#230000
1*
#231000
0*
#232000
b100 @
b100 >
b100 <
b100 :
b11 .
1*
1)
#233000
0*
#234000
1*
#235000
0*
#236000
1*
0)
#237000
0*
#238000
1*
#239000
0*
#240000
0#
b0 .
b11 :
b11 <
b11 >
b11 @
1*
1)
#241000
0*
#242000
1*
#243000
0*
#244000
1*
0)
#245000
0*
#246000
1*
#247000
0*
#248000
b10 @
b10 >
b10 <
b10 :
b1 .
1*
1)
#249000
0*
#250000
1*
#251000
0*
#252000
1*
0)
#253000
0*
#254000
1*
#255000
0*
#256000
0'
0&
0%
0$
b10 .
b1 :
b1 <
b1 >
b1 @
1*
1)
#257000
0*
#258000
1*
#259000
0*
#260000
1*
0)
#261000
0*
#262000
1*
#263000
0*
#264000
b0 @
b0 >
b0 <
b0 :
b11 .
1*
1)
#265000
0*
#266000
1*
#267000
0*
#268000
1*
0)
#269000
0*
#270000
1*
#271000
0*
#272000
b11111011 1
b11111011 8
b11111011 A
1!
1"
1#
b0 .
b111 :
b111 <
b111 >
b111 @
b100 (
b100 /
b100 6
1*
1)
#273000
0*
#274000
1*
#275000
0*
#276000
1*
0)
#277000
0*
#278000
1*
#279000
0*
#280000
1$
1%
1&
1'
b110 @
b110 >
b110 <
b110 :
b1 .
1*
1)
#281000
0*
#282000
1*
#283000
0*
#284000
1*
0)
#285000
0*
#286000
1*
#287000
0*
#288000
b10 .
b101 :
b101 <
b101 >
b101 @
1*
1)
#289000
0*
#290000
1*
#291000
0*
#292000
1*
0)
#293000
0*
#294000
1*
#295000
0*
#296000
b100 @
b100 >
b100 <
b100 :
b11 .
1*
1)
#297000
0*
#298000
1*
#299000
0*
#300000
1*
0)
#301000
0*
#302000
1*
#303000
0*
#304000
0#
b0 .
b11 :
b11 <
b11 >
b11 @
1*
1)
#305000
0*
#306000
1*
#307000
0*
#308000
1*
0)
#309000
0*
#310000
1*
#311000
0*
#312000
b10 @
b10 >
b10 <
b10 :
b1 .
1*
1)
#313000
0*
#314000
1*
#315000
0*
#316000
1*
0)
#317000
0*
#318000
1*
#319000
0*
#320000
0'
0&
0%
0$
b10 .
b1 :
b1 <
b1 >
b1 @
1*
1)
#321000
0*
#322000
1*
#323000
0*
#324000
1*
0)
#325000
0*
#326000
1*
#327000
0*
#328000
b0 @
b0 >
b0 <
b0 :
b11 .
1*
1)
#329000
0*
#330000
1*
#331000
0*
#332000
1*
0)
#333000
0*
#334000
1*
#335000
0*
#336000
b1 1
b1 8
b1 A
0"
1#
b0 .
b111 :
b111 <
b111 >
b111 @
b0 (
b0 /
b0 6
b1 +
b1 0
b1 7
1*
1)
#337000
0*
#338000
1*
#339000
0*
#340000
1*
0)
#341000
0*
#342000
1*
#343000
0*
#344000
1$
1%
1&
1'
b110 @
b110 >
b110 <
b110 :
b1 .
1*
1)
#345000
0*
#346000
1*
#347000
0*
#348000
1*
0)
#349000
0*
#350000
1*
#351000
0*
#352000
b10 .
b101 :
b101 <
b101 >
b101 @
1*
1)
#353000
0*
#354000
1*
#355000
0*
#356000
1*
0)
#357000
0*
#358000
1*
#359000
0*
#360000
b100 @
b100 >
b100 <
b100 :
b11 .
1*
1)
#361000
0*
#362000
1*
#363000
0*
#364000
1*
0)
#365000
0*
#366000
1*
#367000
0*
#368000
0#
b0 .
b11 :
b11 <
b11 >
b11 @
1*
1)
#369000
0*
#370000
1*
#371000
0*
#372000
1*
0)
#373000
0*
#374000
1*
#375000
0*
#376000
b10 @
b10 >
b10 <
b10 :
b1 .
1*
1)
#377000
0*
#378000
1*
#379000
0*
#380000
1*
0)
#381000
0*
#382000
1*
#383000
0*
#384000
0'
0&
0%
0$
b10 .
b1 :
b1 <
b1 >
b1 @
1*
1)
#385000
0*
#386000
1*
#387000
0*
#388000
1*
0)
#389000
0*
#390000
1*
#391000
0*
#392000
b0 @
b0 >
b0 <
b0 :
b11 .
1*
1)
#393000
0*
#394000
1*
#395000
0*
#396000
1*
0)
#397000
0*
#398000
1*
#399000
0*
#400000
b10 1
b10 8
b10 A
0!
1"
1#
b0 .
b111 :
b111 <
b111 >
b111 @
b10 +
b10 0
b10 7
1*
1)
#401000
0*
#402000
1*
#403000
0*
#404000
1*
0)
#405000
0*
#406000
1*
#407000
0*
#408000
1$
1%
1&
1'
b110 @
b110 >
b110 <
b110 :
b1 .
1*
1)
#409000
0*
#410000
1*
#411000
0*
#412000
1*
0)
#413000
0*
#414000
1*
#415000
0*
#416000
b10 .
b101 :
b101 <
b101 >
b101 @
1*
1)
#417000
0*
#418000
1*
#419000
0*
#420000
1*
0)
#421000
0*
#422000
1*
#423000
0*
#424000
b100 @
b100 >
b100 <
b100 :
b11 .
1*
1)
#425000
0*
#426000
1*
#427000
0*
#428000
1*
0)
#429000
0*
#430000
1*
#431000
0*
#432000
0#
b0 .
b11 :
b11 <
b11 >
b11 @
1*
1)
#433000
0*
#434000
1*
#435000
0*
#436000
1*
0)
#437000
0*
#438000
1*
#439000
0*
#440000
b10 @
b10 >
b10 <
b10 :
b1 .
1*
1)
#441000
0*
#442000
1*
#443000
0*
#444000
1*
0)
#445000
0*
#446000
1*
#447000
0*
#448000
0'
0&
0%
0$
b10 .
b1 :
b1 <
b1 >
b1 @
1*
1)
#449000
0*
#450000
1*
#451000
0*
#452000
1*
0)
#453000
0*
#454000
1*
#455000
0*
#456000
b0 @
b0 >
b0 <
b0 :
b11 .
1*
1)
#457000
0*
#458000
1*
#459000
0*
#460000
1*
0)
#461000
0*
#462000
1*
#463000
0*
#464000
b11 1
b11 8
b11 A
0"
1#
b0 .
b111 :
b111 <
b111 >
b111 @
b11 +
b11 0
b11 7
1*
1)
#465000
0*
#466000
1*
#467000
0*
#468000
1*
0)
#469000
0*
#470000
1*
#471000
0*
#472000
1$
1%
1&
1'
b110 @
b110 >
b110 <
b110 :
b1 .
1*
1)
#473000
0*
#474000
1*
#475000
0*
#476000
1*
0)
#477000
0*
#478000
1*
#479000
0*
#480000
b10 .
b101 :
b101 <
b101 >
b101 @
1*
1)
#481000
0*
#482000
1*
#483000
0*
#484000
1*
0)
#485000
0*
#486000
1*
#487000
0*
#488000
b100 @
b100 >
b100 <
b100 :
b11 .
1*
1)
#489000
0*
#490000
1*
#491000
0*
#492000
1*
0)
#493000
0*
#494000
1*
#495000
0*
#496000
0#
b0 .
b11 :
b11 <
b11 >
b11 @
1*
1)
#497000
0*
#498000
1*
#499000
0*
#500000
1*
0)
#501000
0*
#502000
1*
#503000
0*
#504000
b10 @
b10 >
b10 <
b10 :
b1 .
1*
1)
#505000
0*
#506000
1*
#507000
0*
#508000
1*
0)
#509000
0*
#510000
1*
#511000
0*
#512000
0'
0&
0%
0$
b10 .
b1 :
b1 <
b1 >
b1 @
1*
1)
#513000
0*
#514000
1*
#515000
0*
#516000
1*
0)
#517000
0*
#518000
1*
#519000
0*
#520000
b0 @
b0 >
b0 <
b0 :
b11 .
1*
1)
#521000
0*
#522000
1*
#523000
0*
#524000
1*
0)
#525000
0*
#526000
1*
#527000
0*
#528000
b100 1
b100 8
b100 A
1!
1"
1#
b0 .
b111 :
b111 <
b111 >
b111 @
b100 +
b100 0
b100 7
1*
1)
#529000
0*
#530000
1*
#531000
0*
#532000
1*
0)
#533000
0*
#534000
1*
#535000
0*
#536000
1$
1%
1&
1'
b110 @
b110 >
b110 <
b110 :
b1 .
1*
1)
#537000
0*
#538000
1*
#539000
0*
#540000
1*
0)
#541000
0*
#542000
1*
#543000
0*
#544000
b10 .
b101 :
b101 <
b101 >
b101 @
1*
1)
#545000
0*
#546000
1*
#547000
0*
#548000
1*
0)
#549000
0*
#550000
1*
#551000
0*
#552000
b100 @
b100 >
b100 <
b100 :
b11 .
1*
1)
#553000
0*
#554000
1*
#555000
0*
#556000
1*
0)
#557000
0*
#558000
1*
#559000
0*
#560000
0#
b0 .
b11 :
b11 <
b11 >
b11 @
1*
1)
#561000
0*
#562000
1*
#563000
0*
#564000
1*
0)
#565000
0*
#566000
1*
#567000
0*
#568000
b10 @
b10 >
b10 <
b10 :
b1 .
1*
1)
#569000
0*
#570000
1*
#571000
0*
#572000
1*
0)
#573000
0*
#574000
1*
#575000
0*
#576000
0'
0&
0%
0$
b10 .
b1 :
b1 <
b1 >
b1 @
1*
1)
#577000
0*
#578000
1*
#579000
0*
#580000
1*
0)
#581000
0*
#582000
1*
#583000
0*
#584000
b0 @
b0 >
b0 <
b0 :
b11 .
1*
1)
#585000
0*
#586000
1*
#587000
0*
#588000
1*
0)
#589000
0*
#590000
1*
#591000
0*
#592000
b101 1
b101 8
b101 A
0"
1#
b0 .
b111 :
b111 <
b111 >
b111 @
b101 +
b101 0
b101 7
1*
1)
#593000
0*
#594000
1*
#595000
0*
#596000
1*
0)
#597000
0*
#598000
1*
#599000
0*
#600000
1$
1%
1&
1'
b110 @
b110 >
b110 <
b110 :
b1 .
1*
1)
#601000
0*
#602000
1*
#603000
0*
#604000
1*
0)
#605000
0*
#606000
1*
#607000
0*
#608000
b10 .
b101 :
b101 <
b101 >
b101 @
1*
1)
#609000
0*
#610000
1*
#611000
0*
#612000
1*
0)
#613000
0*
#614000
1*
#615000
0*
#616000
b100 @
b100 >
b100 <
b100 :
b11 .
1*
1)
#617000
0*
#618000
1*
#619000
0*
#620000
1*
0)
#621000
0*
#622000
1*
#623000
0*
#624000
0#
b0 .
b11 :
b11 <
b11 >
b11 @
1*
1)
#625000
0*
#626000
1*
#627000
0*
#628000
1*
0)
#629000
0*
#630000
1*
#631000
0*
#632000
b10 @
b10 >
b10 <
b10 :
b1 .
1*
1)
#633000
0*
#634000
1*
#635000
0*
#636000
1*
0)
#637000
0*
#638000
1*
#639000
0*
#640000
0'
0&
0%
0$
b10 .
b1 :
b1 <
b1 >
b1 @
1*
1)
#641000
0*
#642000
1*
#643000
0*
#644000
1*
0)
#645000
0*
#646000
1*
#647000
0*
#648000
b0 @
b0 >
b0 <
b0 :
b11 .
1*
1)
#649000
0*
#650000
1*
#651000
0*
#652000
1*
0)
#653000
0*
#654000
1*
#655000
0*
#656000
b1101 +
b1101 0
b1101 7
0!
1"
1#
b0 .
b111 :
b111 <
b111 >
b111 @
1*
1)
#657000
0*
#658000
1*
#659000
0*
#660000
1*
0)
#661000
0*
#662000
1*
#663000
0*
#664000
1$
1%
1&
1'
b110 @
b110 >
b110 <
b110 :
b1 .
1*
1)
#665000
0*
#666000
1*
#667000
0*
#668000
1*
0)
#669000
0*
#670000
1*
#671000
0*
#672000
b10 .
b101 :
b101 <
b101 >
b101 @
1*
1)
#673000
0*
#674000
1*
#675000
0*
#676000
1*
0)
#677000
0*
#678000
1*
#679000
0*
#680000
b100 @
b100 >
b100 <
b100 :
b11 .
1*
1)
#681000
0*
#682000
1*
#683000
0*
#684000
1*
0)
#685000
0*
#686000
1*
#687000
0*
#688000
0#
b0 .
b11 :
b11 <
b11 >
b11 @
1*
1)
#689000
0*
#690000
1*
#691000
0*
#692000
1*
0)
#693000
0*
#694000
1*
#695000
0*
#696000
b10 @
b10 >
b10 <
b10 :
b1 .
1*
1)
#697000
0*
#698000
1*
#699000
0*
#700000
1*
0)
#701000
0*
#702000
1*
#703000
0*
#704000
0'
0&
0%
0$
b10 .
b1 :
b1 <
b1 >
b1 @
1*
1)
#705000
0*
#706000
1*
#707000
0*
#708000
1*
0)
#709000
0*
#710000
1*
#711000
0*
#712000
b0 @
b0 >
b0 <
b0 :
b11 .
1*
1)
#713000
0*
#714000
1*
#715000
0*
#716000
1*
0)
#717000
0*
#718000
1*
#719000
0*
#720000
b110 (
b110 /
b110 6
b1011101 +
b1011101 0
b1011101 7
b1101 1
b1101 8
b1101 A
0"
1#
b0 .
b111 :
b111 <
b111 >
b111 @
1*
1)
#721000
0*
#722000
1*
#723000
0*
#724000
1*
0)
#725000
0*
#726000
1*
#727000
0*
#728000
1$
1%
1&
1'
b110 @
b110 >
b110 <
b110 :
b1 .
1*
1)
#729000
0*
#730000
1*
#731000
0*
#732000
1*
0)
#733000
0*
#734000
1*
#735000
0*
#736000
b10 .
b101 :
b101 <
b101 >
b101 @
1*
1)
#737000
0*
#738000
1*
#739000
0*
#740000
1*
0)
#741000
0*
#742000
1*
#743000
0*
#744000
b100 @
b100 >
b100 <
b100 :
b11 .
1*
1)
#745000
0*
#746000
1*
#747000
0*
#748000
1*
0)
#749000
0*
#750000
1*
#751000
0*
#752000
0#
b0 .
b11 :
b11 <
b11 >
b11 @
1*
1)
#753000
0*
#754000
1*
#755000
0*
#756000
1*
0)
#757000
0*
#758000
1*
#759000
0*
#760000
b10 @
b10 >
b10 <
b10 :
b1 .
1*
1)
#761000
0*
#762000
1*
#763000
0*
#764000
1*
0)
#765000
0*
#766000
1*
#767000
0*
#768000
0'
0&
0%
0$
b10 .
b1 :
b1 <
b1 >
b1 @
1*
1)
#769000
0*
#770000
1*
#771000
0*
#772000
1*
0)
#773000
0*
#774000
1*
#775000
0*
#776000
b0 @
b0 >
b0 <
b0 :
b11 .
1*
1)
#777000
0*
#778000
1*
#779000
0*
#780000
1*
0)
#781000
0*
#782000
1*
#783000
0*
#784000
b11111101 1
b11111101 8
b11111101 A
1!
1"
1#
b0 .
b111 :
b111 <
b111 >
b111 @
1*
1)
