Modulos/ByteStriping/striping.v
`timescale 1ns/1ps

module striping (clk, fromMux, TL0, TL1, TL2,TL3);
input clk;
input [7:0] fromMux;

output [7:0] TL0;
output [7:0] TL1;
output [7:0] TL2;
output [7:0] TL3;

reg [7:0] TL0;
reg [7:0] TL1;
reg [7:0] TL2;
reg [7:0] TL3;

reg [1:0] c; //Contador para ver que lane se debe usar

reg D; // D=0 => no estamos transmitiendo datos || D=1 => estamos transmitiendo datos


parameter COM = 8'hBC,PAD = 8'hF7,SKP = 8'h1C,STP = 8'hFB, SDP = 8'h5C ;
parameter END = 8'hFD,EDB = 8'hFE,FTS = 8'h3C,IDL = 8'h7C;

//D <= 1'b0; 

always @ (posedge clk) begin
      if (D) begin
            if (fromMux == END) begin
            TL3<= fromMux;
            D<=0;
            c <= 2'b00;
            end else begin
                  if (c==2'b00) begin
                        TL0 <= fromMux;
                        c <= c+1;
                  end else if (c==2'b01) begin
                        TL1 <= fromMux;
                        c <= c+1;
                        
                  end else if (c==2'b10) begin
                        TL2 <= fromMux;
                        c <= c+1;
                        
                  end else if (c==2'b11) begin
                        TL3 <= fromMux;
                        c <= c+1;
                        end  
            end //end else de            
      end else begin
      
            if (fromMux == STP) begin
            D<=1;
            TL0 <= fromMux;
            c <= 2'b01;
            end  
            if (fromMux == SDP) begin
            D<=1;
            TL0 <= fromMux;
            c <= c+1;
            end

            if (fromMux == IDL) begin
            c <= 2'b00;
            TL0 <= fromMux;
            TL1 <= fromMux;
            TL2 <= fromMux;
            TL3 <= fromMux;
            end

            if (fromMux == COM) begin
            c <= 2'b00;
            TL0 <= fromMux;
            TL1 <= fromMux;
            TL2 <= fromMux;
            TL3 <= fromMux;
            end


            if (fromMux == SKP) begin
            c <= 2'b00;
            TL0 <= fromMux;
            TL1 <= fromMux;
            TL2 <= fromMux;
            TL3 <= fromMux;
            end
      end  //else de if (D)



end //always




      





      /*
      always @ ( * ) begin
      case(fromMux)
      STP : begin
            c = 1'b00; // contador == 00
            if(fromMux=END) begin
                  TL3 = fromMux;
                  end else begin
                  //ACOMODAR LOS BICHOS EN EL LANE CORRESPONDIENTE E INCREMENTAR EL CONTADOR
                  end
                  
            end

      SDP : TL0 = fromMux; //Start

      END : TL3 = fromMux;

      //EDB : TL3 = fromMux;

      SKP : begin
            TL0 = fromMux;
            TL1 = fromMux;
            TL2 = fromMux;
            TL3 = fromMux;
            end
      
      IDL : begin
            c = 1'b00;
            TL0 = fromMux;
            TL1 = fromMux;
            TL2 = fromMux;
            TL3 = fromMux;
            end
      


      end

      */

endmodule


      /*
      -value en 1, y selec de mux para que mande IDLE

      -Start-Datoooooos-End, Verificar multiplos de 4 bytes para que el END quede en el ultimo
      Mandar datos por multiplos de 4 bytes, contando Start y END



      */

Modulos/ByteStriping/TBStriping.v
`include "striping.v"

module TBStriping;
    reg clk;
    reg [7:0] fromMux;

    wire [7:0] TL0;
    wire [7:0] TL1;
    wire [7:0] TL2;
    wire [7:0] TL3;

    striping byteStp (.clk(clk), .fromMux(fromMux), .TL0(TL0), .TL1(TL1), .TL2(TL2),.TL3(TL3));

    always #1 clk = !clk; //clk sgl.

    initial begin
    $display ("------------------------------test striping-------------------------------");
    $dumpvars;
    $display ("time\t    clk,      fromMux,    TL0   ,    TL1   ,   TL2   ,   TL3   ");
    $monitor ("%g\t      %b          %h         %h        %h         %h        %h",
    $time, clk, fromMux, TL0, TL1, TL2,TL3);

    clk <= 0;
    #4
    $display ("------------------------------Agregamos SKIPS (SKP = 1C) -------------------------------");
    fromMux = 8'h1C; //SKP
    #6
        $display ("------------------------------Agregamos IDLE (IDL = 7C) -------------------------------");

    fromMux = 8'h7C; //IDLE
    #6
        $display ("------------------------------Agregamos START (STP = FB) -------------------------------");

    fromMux = 8'hFB; //STP
    #2
    $display ("------------Agregamos 6 bytes seguidos de DATOS (en este caso FF simbolizan datos) ------------");
    fromMux = 8'h01;
    #2
    fromMux = 8'h02;
    #2
    fromMux = 8'h03;
    #2
    fromMux = 8'h04;
    #2
    fromMux = 8'h05;
    #2
    fromMux = 8'h06;
    #2
    $display ("------------------------------Agregamos END (END = ) -------------------------------");
    fromMux = 8'hFD;
    #2
    $display ("Podemos ver como inicialmente se detecta un START, se manda al LANE0, y se siguen recibiendo datos hasta que se recibe el END");
    $finish;
    end

    endmodule

Modulos/ByteStriping/dump.vcd
$date
	Fri Jun  1 12:14:39 2018
$end
$version
	Icarus Verilog
$end
$timescale
	1ps
$end
$scope module TBStriping $end
$var wire 8 ! TL3 [7:0] $end
$var wire 8 " TL2 [7:0] $end
$var wire 8 # TL1 [7:0] $end
$var wire 8 $ TL0 [7:0] $end
$var reg 1 % clk $end
$var reg 8 & fromMux [7:0] $end
$scope module byteStp $end
$var wire 1 % clk $end
$var wire 8 ' fromMux [7:0] $end
$var reg 1 ( D $end
$var reg 8 ) TL0 [7:0] $end
$var reg 8 * TL1 [7:0] $end
$var reg 8 + TL2 [7:0] $end
$var reg 8 , TL3 [7:0] $end
$var reg 2 - c [1:0] $end
$upscope $end
$upscope $end
$enddefinitions $end
#0
$dumpvars
bx -
bx ,
bx +
bx *
bx )
x(
bx '
bx &
0%
bx $
bx #
bx "
bx !
$end
#1000
1%
#2000
0%
#3000
1%
#4000
0%
b11100 &
b11100 '
#5000
b11100 !
b11100 ,
b11100 "
b11100 +
b11100 #
b11100 *
b11100 $
b11100 )
b0 -
1%
#6000
0%
#7000
1%
#8000
0%
#9000
1%
#10000
0%
b1111100 &
b1111100 '
#11000
b1111100 !
b1111100 ,
b1111100 "
b1111100 +
b1111100 #
b1111100 *
b1111100 $
b1111100 )
1%
#12000
0%
#13000
1%
#14000
0%
#15000
1%
#16000
0%
b11111011 &
b11111011 '
#17000
b1 -
b11111011 $
b11111011 )
1(
1%
#18000
0%
b1 &
b1 '
#19000
b10 -
b1 #
b1 *
1%
#20000
0%
b10 &
b10 '
#21000
b11 -
b10 "
b10 +
1%
#22000
0%
b11 &
b11 '
#23000
b0 -
b11 !
b11 ,
1%
#24000
0%
b100 &
b100 '
#25000
b1 -
b100 $
b100 )
1%
#26000
0%
b101 &
b101 '
#27000
b10 -
b101 #
b101 *
1%
#28000
0%
b110 &
b110 '
#29000
b11 -
b110 "
b110 +
1%
#30000
0%
b11111101 &
b11111101 '
#31000
b0 -
0(
b11111101 !
b11111101 ,
1%
