Modulos/Mux_Ctrl/MuxCtrl.v
module MuxCtrl(

input clk,
input [7:0] data,
input enb,
input [3:0] S,
output [7:0] outmux

);

reg outmux;

parameter COM = 8'hBC,PAD = 8'hF7,SKP = 8'h1C,STP = 8'hFB, SDP = 8'h5C ;
parameter END = 8'hFD,EDB = 8'hFE,FTS = 8'h3C,IDL = 8'h7C;

always @ (posedge clk)
  begin
    if (enb) begin
      case(S)
        4'b0000 : outmux = data;

        4'b0001 : outmux = COM;

        4'b0010 : outmux = PAD;

        4'b0011 : outmux = SKP;

        4'b0100 : outmux = STP;

        4'b0101 : outmux = SDP;

        4'b0110 : outmux = END;

        4'b0111 : outmux = EDB;

        4'b1000 : outmux = FTS;

        4'b1001 : outmux = IDL;
      endcase
    end
  end
  endmodule

Modulos/Mux_Ctrl/testb.v
//Pruebas para Registro Desplazable 4 bits
//Bryan Cervantes Ramirez- B31726
`include "MuxCtrl.v"
module test;

reg clk;
reg [7:0] data;
reg enb;
reg [3:0] S;
wire [7:0] outmux;


	MuxCtrl Mux1(.clk(clk), .data(data), .enb(enb), .S(S), .outmux(outmux));

	always #2 clk = !clk;

	initial begin
	$display ("Mux test");
  $dumpvars;
  $display ("time\t     data  ,	       enb ,       S ,    outmux      ");
  $monitor ("%g\t      %h	   	%h          %h       %h            ",
  $time, data ,enb ,S ,outmux);

		$display("-----Test Mux de Control----");
		//Valores iniciales:
		clk <=0;
		enb <= 1;
		#2
		data <= 4'b1010;
		S <= 4'b0000;
		#8
		S <= 4'b0010;
		#8
		$display("-----STP Signal-----");
		S <= 4'b0100;
		#6
		$display("-----SDP Signal-----");
		S <= 4'b0101;
		#6
		$display("-----END Signal-----");
		S <= 4'b0110;
		#6
		$display("-----IDL Signal-----");
		S <= 4'b1001;
		#6
		$display("-----SKṔ Signal-----");
		S <= 4'b0011;
		#6



		$finish;
	    end
endmodule

Modulos/Mux_Ctrl/dump.vcd
$date
	Wed May 30 00:38:53 2018
$end
$version
	Icarus Verilog
$end
$timescale
	1s
$end
$scope module test $end
$var wire 8 ! outmux [7:0] $end
$var reg 4 " S [3:0] $end
$var reg 1 # clk $end
$var reg 8 $ data [7:0] $end
$var reg 1 % enb $end
$scope module Mux1 $end
$var wire 4 & S [3:0] $end
$var wire 1 # clk $end
$var wire 8 ' data [7:0] $end
$var wire 1 % enb $end
$var reg 8 ( outmux [7:0] $end
$upscope $end
$upscope $end
$enddefinitions $end
#0
$dumpvars
bx (
bx '
bx &
1%
bx $
0#
bx "
bx !
$end
#2
b0 "
b0 &
b1010 $
b1010 '
1#
#4
0#
#6
b1010 !
b1010 (
1#
#8
0#
#10
b10 "
b10 &
1#
#12
0#
#14
b11110111 !
b11110111 (
1#
#16
0#
#18
b100 "
b100 &
1#
#20
0#
#22
b11111011 !
b11111011 (
1#
#24
b101 "
b101 &
0#
#26
b1011100 !
b1011100 (
1#
#28
0#
#30
b110 "
b110 &
1#
#32
0#
#34
b11111101 !
b11111101 (
1#
#36
b1001 "
b1001 &
0#
#38
b1111100 !
b1111100 (
1#
#40
0#
#42
b11 "
b11 &
1#
#44
0#
#46
b11100 !
b11100 (
1#
